openwillis/__init__.py
openwillis-3.1.0.dist-info/METADATA
openwillis-3.1.0.dist-info/WHEEL
openwillis-3.1.0.dist-info/top_level.txt
openwillis-3.1.0.dist-info/RECORD
