Metadata-Version: 2.4
Name: openwillis
Version: 3.1.0
Summary: digital health measurement
Home-page: https://github.com/bklynhlth/openwillis
Author: bklynhlth
Author-email: admin@bklynhlth.com
License: Apache
Requires-Python: >=3.9, <3.11
Requires-Dist: openwillis-voice==1.1.0
Requires-Dist: openwillis-transcribe==1.1.0
Requires-Dist: openwillis-gps==1.1.0
Requires-Dist: openwillis-speech==1.1.0
Requires-Dist: openwillis-face==1.1.0
Dynamic: author
Dynamic: author-email
Dynamic: description
Dynamic: description-content-type
Dynamic: home-page
Dynamic: license
Dynamic: requires-dist
Dynamic: requires-python
Dynamic: summary
